awgan/__init__.py
awgan/model.py
awgan/preprocessing.py
awgan-0.1.0.dist-info/LICENSE
awgan-0.1.0.dist-info/METADATA
awgan-0.1.0.dist-info/WHEEL
awgan-0.1.0.dist-info/top_level.txt
awgan-0.1.0.dist-info/RECORD
