Metadata-Version: 2.1
Name: awgan
Version: 0.1.0
Summary: code for model AWGAN
Home-page: https://github.com/HelloWorldLTY/AWGAN
Author: tianyu liu
Author-email: tianyul4@illinois.edu
License: UNKNOWN
Keywords: single-cell,rna,GAN,deep learning
Platform: UNKNOWN
License-File: LICENSE
Requires-Dist: torch
Requires-Dist: numpy
Requires-Dist: scanpy
Requires-Dist: numba
Requires-Dist: scikit-misc
Requires-Dist: graphtools
